{
  "color-space-for-untagged-svg-colors" : "display-p3",
  "fill-specializations" : [
    {
      "value" : "automatic"
    },
    {
      "appearance" : "dark",
      "value" : "automatic"
    }
  ],
  "groups" : [
    {
      "blend-mode-specializations" : [
        {
          "value" : "normal"
        },
        {
          "appearance" : "dark",
          "value" : "normal"
        }
      ],
      "blur-material-specializations" : [
        {
          "value" : 0.34
        },
        {
          "appearance" : "dark",
          "value" : null
        },
        {
          "appearance" : "tinted",
          "value" : null
        }
      ],
      "hidden" : false,
      "layers" : [
        {
          "hidden" : false,
          "image-name" : "NES Controller.svg",
          "name" : "NES Controller",
          "position" : {
            "scale" : 1.1,
            "translation-in-points" : [
              82.8,
              188
            ]
          }
        }
      ],
      "lighting-specializations" : [
        {
          "value" : "individual"
        },
        {
          "appearance" : "dark",
          "value" : "combined"
        },
        {
          "appearance" : "tinted",
          "value" : "combined"
        }
      ],
      "opacity" : 1,
      "shadow-specializations" : [
        {
          "value" : {
            "kind" : "layer-color",
            "opacity" : 0.69
          }
        },
        {
          "appearance" : "dark",
          "value" : {
            "kind" : "layer-color",
            "opacity" : 0.69
          }
        }
      ],
      "specular-specializations" : [
        {
          "value" : true
        },
        {
          "appearance" : "dark",
          "value" : false
        },
        {
          "appearance" : "tinted",
          "value" : false
        }
      ],
      "translucency-specializations" : [
        {
          "value" : {
            "enabled" : true,
            "value" : 0.08
          }
        },
        {
          "appearance" : "dark",
          "value" : {
            "enabled" : true,
            "value" : 0.08
          }
        },
        {
          "appearance" : "tinted",
          "value" : {
            "enabled" : true,
            "value" : 0.08
          }
        }
      ]
    },
    {
      "blend-mode-specializations" : [
        {
          "value" : "hard-light"
        },
        {
          "appearance" : "dark",
          "value" : "normal"
        },
        {
          "appearance" : "tinted",
          "value" : "hard-light"
        }
      ],
      "blur-material" : 0.1,
      "layers" : [
        {
          "fill-specializations" : [
            {
              "value" : {
                "solid" : "srgb:1.00000,0.14913,0.00000,1.00000"
              }
            },
            {
              "appearance" : "tinted",
              "value" : {
                "solid" : "srgb:0.92143,0.92145,0.92144,1.00000"
              }
            }
          ],
          "glass" : true,
          "hidden" : false,
          "image-name" : "Light 1.svg",
          "name" : "Light 1",
          "position" : {
            "scale" : 1.16,
            "translation-in-points" : [
              -293,
              -188
            ]
          }
        },
        {
          "blend-mode" : "normal",
          "fill-specializations" : [
            {
              "value" : {
                "solid" : "extended-srgb:1.00000,0.80000,0.00000,1.00000"
              }
            },
            {
              "appearance" : "tinted",
              "value" : {
                "solid" : "srgb:0.92143,0.92145,0.92144,1.00000"
              }
            }
          ],
          "hidden" : false,
          "image-name" : "Light 2.svg",
          "name" : "Light 2",
          "position" : {
            "scale" : 1.16,
            "translation-in-points" : [
              -293,
              -5
            ]
          }
        },
        {
          "fill-specializations" : [
            {
              "value" : {
                "solid" : "extended-srgb:0.20392,0.78039,0.34902,1.00000"
              }
            },
            {
              "appearance" : "tinted",
              "value" : {
                "solid" : "srgb:0.92143,0.92145,0.92144,1.00000"
              }
            }
          ],
          "image-name" : "Light 3.svg",
          "name" : "Light 3",
          "position" : {
            "scale" : 1.16,
            "translation-in-points" : [
              -293,
              170
            ]
          }
        }
      ],
      "lighting-specializations" : [
        {
          "value" : "individual"
        },
        {
          "appearance" : "tinted",
          "value" : "individual"
        }
      ],
      "shadow-specializations" : [
        {
          "value" : {
            "kind" : "neutral",
            "opacity" : 0.3
          }
        },
        {
          "appearance" : "dark",
          "value" : {
            "kind" : "neutral",
            "opacity" : 0.3
          }
        },
        {
          "appearance" : "tinted",
          "value" : {
            "kind" : "neutral",
            "opacity" : 0.8
          }
        }
      ],
      "specular" : true,
      "translucency-specializations" : [
        {
          "value" : {
            "enabled" : false,
            "value" : 0.3
          }
        },
        {
          "appearance" : "dark",
          "value" : {
            "enabled" : false,
            "value" : 0.3
          }
        },
        {
          "appearance" : "tinted",
          "value" : {
            "enabled" : false,
            "value" : 0.3
          }
        }
      ]
    },
    {
      "blend-mode" : "screen",
      "blur-material" : null,
      "layers" : [
        {
          "fill" : {
            "solid" : "extended-gray:1.00000,1.00000"
          },
          "glass" : true,
          "image-name" : "Rectangle.svg",
          "name" : "Rectangle",
          "position" : {
            "scale" : 1.16,
            "translation-in-points" : [
              87,
              -8
            ]
          }
        }
      ],
      "lighting" : "individual",
      "shadow" : {
        "kind" : "neutral",
        "opacity" : 0.5
      },
      "translucency" : {
        "enabled" : true,
        "value" : 0.35
      }
    },
    {
      "blur-material" : 0.5,
      "hidden" : false,
      "layers" : [
        {
          "blend-mode" : "normal",
          "fill-specializations" : [
            {
              "value" : {
                "solid" : "display-p3:0.13405,0.13405,0.13405,1.00000"
              }
            },
            {
              "appearance" : "dark",
              "value" : {
                "solid" : "display-p3:0.24836,0.24877,0.24877,1.00000"
              }
            },
            {
              "appearance" : "tinted",
              "value" : {
                "solid" : "display-p3:0.24836,0.24877,0.24877,1.00000"
              }
            }
          ],
          "glass" : true,
          "hidden" : false,
          "image-name" : "Rack.svg",
          "name" : "Rack",
          "position" : {
            "scale" : 1.16,
            "translation-in-points" : [
              0,
              -8
            ]
          }
        }
      ],
      "lighting" : "individual",
      "shadow-specializations" : [
        {
          "value" : {
            "kind" : "layer-color",
            "opacity" : 0.8
          }
        },
        {
          "appearance" : "dark",
          "value" : {
            "kind" : "layer-color",
            "opacity" : 0.8
          }
        },
        {
          "appearance" : "tinted",
          "value" : {
            "kind" : "layer-color",
            "opacity" : 0.8
          }
        }
      ],
      "specular" : false,
      "translucency" : {
        "enabled" : false,
        "value" : 0.5
      }
    }
  ],
  "supported-platforms" : {
    "circles" : [
      "watchOS"
    ],
    "squares" : "shared"
  }
}